{"assets":{"1500BA2D3FD472877CC669AF3A91040F":{"type":"texture","index":3,"assetRequest":{"type":"slide","state":"contents","slide":"EE61624D-2470-41AB-A0C1-3FBF0E1F0368"},"url":{"web":"assets/EE61624D-2470-41AB-A0C1-3FBF0E1F0368.svgmap"},"width":1752,"height":238},"62358F665A19968F6EA1D3132EDD5855":{"type":"texture","index":7,"assetRequest":{"type":"slide","state":"outgoing","slide":"EE61624D-2470-41AB-A0C1-3FBF0E1F0368"},"url":{"web":"assets/EE61624D-2470-41AB-A0C1-3FBF0E1F0368.svgmap"},"width":1920,"height":1080},"C25C25FF361FB24FC35F6B120D2F252D":{"type":"texture","index":0,"assetRequest":{"type":"slide","state":"contents","slide":"EE61624D-2470-41AB-A0C1-3FBF0E1F0368"},"url":{"web":"assets/EE61624D-2470-41AB-A0C1-3FBF0E1F0368.svgmap"},"width":1920,"height":1080},"5FCE00F3DF63E38504E7C0DA8D811BD5":{"type":"texture","index":4,"assetRequest":{"type":"slide","state":"contents","slide":"EE61624D-2470-41AB-A0C1-3FBF0E1F0368"},"url":{"web":"assets/EE61624D-2470-41AB-A0C1-3FBF0E1F0368.svgmap"},"width":749,"height":88},"634618DBDF2F96BD355070A8377C1141":{"type":"texture","index":2,"assetRequest":{"type":"slide","state":"contents","slide":"EE61624D-2470-41AB-A0C1-3FBF0E1F0368"},"url":{"web":"assets/EE61624D-2470-41AB-A0C1-3FBF0E1F0368.svgmap"},"width":211,"height":29},"EA63DAD110C22677C2F356C304939719":{"type":"texture","index":1,"assetRequest":{"type":"slide","state":"contents","slide":"EE61624D-2470-41AB-A0C1-3FBF0E1F0368"},"url":{"web":"assets/EE61624D-2470-41AB-A0C1-3FBF0E1F0368.svgmap"},"width":968,"height":622},"A324682FF46FB156BE950BD2455312FC":{"type":"texture","index":8,"assetRequest":{"type":"slide","state":"incoming","slide":"FF5EDFC7-810C-4E9A-BBCB-22EEB2026C6B"},"url":{"web":"assets/EE61624D-2470-41AB-A0C1-3FBF0E1F0368.svgmap"},"width":1920,"height":1080},"2D4B9D275A36EEB34B2C475DF53DFB56":{"type":"texture","index":5,"assetRequest":{"type":"slide","state":"contents","slide":"EE61624D-2470-41AB-A0C1-3FBF0E1F0368"},"url":{"web":"assets/EE61624D-2470-41AB-A0C1-3FBF0E1F0368.svgmap"},"width":1752,"height":172},"D79AAE7B1AFA8551C9BD5FB5E9E680D2":{"type":"texture","index":6,"assetRequest":{"type":"slide","state":"contents","slide":"EE61624D-2470-41AB-A0C1-3FBF0E1F0368"},"url":{"web":"assets/EE61624D-2470-41AB-A0C1-3FBF0E1F0368.svgmap"},"width":1648,"height":645}},"events":[{"effects":[{"beginTime":0,"baseLayer":{"animations":[],"initialState":{"affineTransform":[1,0,0,1,0,0],"masksToBounds":false,"rotation":0,"scale":1,"position":{"pointX":988.2249683937771,"pointY":292.8644268728995},"width":1749.265549580523,"sublayerTransform":[1,0,0,0,0,1,0,0,0,0,1,0,0,0,0,1],"contentsRect":{"y":0,"x":0,"width":1,"height":1},"opacity":1,"edgeAntialiasingMask":251658240,"height":204.3999914690448,"hidden":false,"anchorPoint":{"pointX":0.5,"pointY":0.5}},"objectID":"939E5D0B-CBCC-4E8C-899F-C751A8CD494A","layers":[{"animations":[],"initialState":{"affineTransform":[1,0,0,1,0,0],"masksToBounds":false,"rotation":0,"scale":1,"position":{"pointX":846.4078063964844,"pointY":349.335568861623},"width":1749.265549580523,"sublayerTransform":[1,0,0,0,0,1,0,0,0,0,1,-0.0003500791246677598,0,0,0,1],"contentsRect":{"y":0,"x":0,"width":1,"height":1},"opacity":1,"edgeAntialiasingMask":251658240,"height":204.3999914690448,"hidden":false,"anchorPoint":{"pointX":0.4838646748628043,"pointY":1.709078196877164}},"layers":[{"animations":[{"timeOffset":0,"from":{"scalar":false},"beginTime":1e-100,"repeatCount":0,"fillMode":"both","property":"hidden","autoreverses":false,"duration":0.01,"to":{"scalar":true}}],"layers":[],"texturedRectangle":{"singleTextureOpacity":1,"textXHeight":0.1224354976365546,"textBaseline":0.9392314449893521,"isBackgroundTexture":true,"isVerticalText":false,"textColor":[0,0,0,1],"textureType":6},"initialState":{"affineTransform":[1,0,0,1,0,0],"masksToBounds":false,"rotation":0,"scale":1,"position":{"pointX":875.4078063964844,"pointY":84.33556886162296},"width":1752,"sublayerTransform":[1,0,0,0,0,1,0,0,0,0,1,0,0,0,0,1],"contentsRect":{"y":0,"x":0,"width":1,"height":1},"opacity":1,"edgeAntialiasingMask":0,"height":238,"hidden":false,"anchorPoint":{"pointX":0.5,"pointY":0.5}},"texture":"1500BA2D3FD472877CC669AF3A91040F"}]}]},"effects":[{"beginTime":0,"baseLayer":{"animations":[],"initialState":{"affineTransform":[1,0,0,1,0,0],"masksToBounds":false,"rotation":0,"scale":1,"position":{"pointX":988.2249683937771,"pointY":259.7144258833086},"width":1749.265549580523,"sublayerTransform":[1,0,0,0,0,1,0,0,0,0,1,0,0,0,0,1],"contentsRect":{"y":0,"x":0,"width":1,"height":1},"opacity":1,"edgeAntialiasingMask":251658240,"height":138.6999934482265,"hidden":false,"anchorPoint":{"pointX":0.5,"pointY":0.5}},"objectID":"E008FA27-5859-416D-985D-4252CC80A681","layers":[{"animations":[],"initialState":{"affineTransform":[1,0,0,1,0,0],"masksToBounds":false,"rotation":0,"scale":1,"position":{"pointX":846.4078063964844,"pointY":349.6355708408046},"width":1749.265549580523,"sublayerTransform":[1,0,0,0,0,1,0,0,0,0,1,-0.0003500791246677598,0,0,0,1],"contentsRect":{"y":0,"x":0,"width":1,"height":1},"opacity":1,"edgeAntialiasingMask":251658240,"height":138.6999934482265,"hidden":false,"anchorPoint":{"pointX":0.4838646748628043,"pointY":2.520804523118565}},"layers":[{"animations":[{"timeOffset":0,"from":{"scalar":true},"beginTime":1e-100,"repeatCount":0,"fillMode":"both","property":"hidden","autoreverses":false,"duration":0.01,"to":{"scalar":false}}],"layers":[],"texturedRectangle":{"singleTextureOpacity":1,"textXHeight":0.1694165606831395,"textBaseline":0.9159132771438361,"isBackgroundTexture":true,"isVerticalText":false,"textColor":[0,0,0,1],"textureType":6},"initialState":{"affineTransform":[1,0,0,1,0,0],"masksToBounds":false,"rotation":0,"scale":1,"position":{"pointX":875.4078063964844,"pointY":51.63557084080458},"width":1752,"sublayerTransform":[1,0,0,0,0,1,0,0,0,0,1,0,0,0,0,1],"contentsRect":{"y":0,"x":0,"width":1,"height":1},"opacity":1,"edgeAntialiasingMask":0,"height":172,"hidden":true,"anchorPoint":{"pointX":0.5,"pointY":0.5}},"texture":"2D4B9D275A36EEB34B2C475DF53DFB56"}]}]},"effects":[],"duration":0.01,"type":"buildIn","name":"apple:appear","objectID":"E008FA27-5859-416D-985D-4252CC80A681"}],"duration":0.01,"type":"buildOut","name":"apple:appear","objectID":"939E5D0B-CBCC-4E8C-899F-C751A8CD494A"}],"automaticPlay":false,"hyperlinks":[],"accessibility":[{"text":"Delta morphology","targetRectangle":{"y":31.72067832946777,"x":612.0501708984375,"width":752.349609375,"height":115}},{"text":"School of Geosciences","targetRectangle":{"y":1039.375854492188,"x":1701.960205078125,"width":199.053955078125,"height":25}},{"text":"coast2000kolb.jpg","targetRectangle":{"y":432.3339233398438,"x":488.899169921875,"width":949.99853515625,"height":603.3535766601562}},{"text":"The distributaries and main channel of the rivers forming deltas typically move to find the shortest route to the sea, and this causes shifting of the active locus of deposition on deltas. ","targetRectangle":{"y":190.664431138377,"x":165.1199706792831,"width":1697.73772585392,"height":204.3999965190887}}],"baseLayer":{"animations":[],"initialState":{"affineTransform":[1,0,0,1,0,0],"masksToBounds":false,"rotation":0,"scale":1,"position":{"pointX":960,"pointY":540},"width":1920,"sublayerTransform":[1,0,0,0,0,1,0,0,0,0,1,0,0,0,0,1],"contentsRect":{"y":0,"x":0,"width":1,"height":1},"opacity":1,"edgeAntialiasingMask":251658240,"height":1080,"hidden":false,"anchorPoint":{"pointX":0.5,"pointY":0.5}},"layers":[{"animations":[],"initialState":{"affineTransform":[1,0,0,1,0,0],"masksToBounds":false,"rotation":0,"scale":1,"position":{"pointX":960,"pointY":540},"width":1920,"sublayerTransform":[1,0,0,0,0,1,0,0,0,0,1,0,0,0,0,1],"contentsRect":{"y":0,"x":0,"width":1,"height":1},"opacity":1,"edgeAntialiasingMask":251658240,"height":1080,"hidden":false,"anchorPoint":{"pointX":0.5,"pointY":0.5}},"layers":[{"animations":[],"initialState":{"affineTransform":[1,0,0,1,0,0],"masksToBounds":false,"rotation":0,"scale":1,"position":{"pointX":960,"pointY":540},"width":1920,"sublayerTransform":[1,0,0,0,0,1,0,0,0,0,1,0,0,0,0,1],"contentsRect":{"y":0,"x":0,"width":1,"height":1},"opacity":1,"edgeAntialiasingMask":251658240,"height":1080,"hidden":false,"anchorPoint":{"pointX":0.5,"pointY":0.5}},"layers":[{"animations":[],"layers":[],"texturedRectangle":{"isBackgroundTexture":true,"singleTextureOpacity":1,"textureType":1,"textBaseline":0,"textXHeight":0,"isVerticalText":false},"initialState":{"affineTransform":[1,0,0,1,0,0],"masksToBounds":false,"rotation":0,"scale":1,"position":{"pointX":960,"pointY":540},"width":1920,"sublayerTransform":[1,0,0,0,0,1,0,0,0,0,1,0,0,0,0,1],"contentsRect":{"y":0,"x":0,"width":1,"height":1},"opacity":1,"edgeAntialiasingMask":0,"height":1080,"hidden":false,"anchorPoint":{"pointX":0.5,"pointY":0.5}},"texture":"C25C25FF361FB24FC35F6B120D2F252D"}]}]},{"animations":[],"initialState":{"affineTransform":[1,0,0,1,0,0],"masksToBounds":false,"rotation":0,"scale":1,"position":{"pointX":960,"pointY":540},"width":1920,"sublayerTransform":[1,0,0,0,0,1,0,0,0,0,1,0,0,0,0,1],"contentsRect":{"y":0,"x":0,"width":1,"height":1},"opacity":1,"edgeAntialiasingMask":251658240,"height":1080,"hidden":false,"anchorPoint":{"pointX":0.5,"pointY":0.5}},"layers":[{"animations":[],"initialState":{"affineTransform":[1,0,0,1,0,0],"masksToBounds":false,"rotation":0,"scale":1,"position":{"pointX":963.8984375,"pointY":734.0107116699219},"width":949.99853515625,"sublayerTransform":[1,0,0,0,0,1,0,0,0,0,1,0,0,0,0,1],"contentsRect":{"y":0,"x":0,"width":1,"height":1},"opacity":1,"edgeAntialiasingMask":251658240,"height":603.3535766601562,"hidden":false,"anchorPoint":{"pointX":0.5,"pointY":0.5}},"objectID":"F705B79F-3D80-4145-AEE6-A52BEB992010","layers":[{"animations":[],"layers":[],"texturedRectangle":{"isBackgroundTexture":true,"singleTextureOpacity":1,"textureType":5,"textBaseline":0,"textXHeight":0,"isVerticalText":false},"initialState":{"affineTransform":[1,0,0,1,0,0],"masksToBounds":false,"rotation":0,"scale":1,"position":{"pointX":475.100830078125,"pointY":301.6660766601562},"width":968,"sublayerTransform":[1,0,0,0,0,1,0,0,0,0,1,0,0,0,0,1],"contentsRect":{"y":0,"x":0,"width":1,"height":1},"opacity":1,"edgeAntialiasingMask":0,"height":622,"hidden":false,"anchorPoint":{"pointX":0.5,"pointY":0.5}},"texture":"EA63DAD110C22677C2F356C304939719"}]}]},{"animations":[],"initialState":{"affineTransform":[1,0,0,1,0,0],"masksToBounds":false,"rotation":0,"scale":1,"position":{"pointX":960,"pointY":540},"width":1920,"sublayerTransform":[1,0,0,0,0,1,0,0,0,0,1,0,0,0,0,1],"contentsRect":{"y":0,"x":0,"width":1,"height":1},"opacity":1,"edgeAntialiasingMask":251658240,"height":1080,"hidden":false,"anchorPoint":{"pointX":0.5,"pointY":0.5}},"layers":[{"animations":[],"initialState":{"affineTransform":[1,0,0,1,0,0],"masksToBounds":false,"rotation":0,"scale":1,"position":{"pointX":1801.487178325653,"pointY":1053.904336541891},"width":211.8828039169312,"sublayerTransform":[1,0,0,0,0,1,0,0,0,0,1,0,0,0,0,1],"contentsRect":{"y":0,"x":0,"width":1,"height":1},"opacity":1,"edgeAntialiasingMask":251658240,"height":40.3069640994072,"hidden":false,"anchorPoint":{"pointX":0.5,"pointY":0.5}},"objectID":"6B8CF862-225A-49B5-AF89-FBF00406E318","layers":[{"animations":[],"layers":[],"texturedRectangle":{"singleTextureOpacity":1,"textXHeight":0.3554771686422414,"textBaseline":0.5821617389547413,"isBackgroundTexture":true,"isVerticalText":false,"textColor":[0,0,0,1],"textureType":6},"initialState":{"affineTransform":[1,0,0,1,0,0],"masksToBounds":false,"rotation":0,"scale":1,"position":{"pointX":110.9542236328125,"pointY":22.7491455078125},"width":211,"sublayerTransform":[1,0,0,0,0,1,0,0,0,0,1,0,0,0,0,1],"contentsRect":{"y":0,"x":0,"width":1,"height":1},"opacity":1,"edgeAntialiasingMask":0,"height":29,"hidden":false,"anchorPoint":{"pointX":0.5,"pointY":0.5}},"texture":"634618DBDF2F96BD355070A8377C1141"}]}]},{"animations":[],"initialState":{"affineTransform":[1,0,0,1,0,0],"masksToBounds":false,"rotation":0,"scale":1,"position":{"pointX":960,"pointY":540},"width":1920,"sublayerTransform":[1,0,0,0,0,1,0,0,0,0,1,0,0,0,0,1],"contentsRect":{"y":0,"x":0,"width":1,"height":1},"opacity":1,"edgeAntialiasingMask":251658240,"height":1080,"hidden":false,"anchorPoint":{"pointX":0.5,"pointY":0.5}},"layers":[{"animations":[],"initialState":{"affineTransform":[1,0,0,1,0,0],"masksToBounds":false,"rotation":0,"scale":1,"position":{"pointX":988.2249683937771,"pointY":292.8644268728995},"width":1749.265549580523,"sublayerTransform":[1,0,0,0,0,1,0,0,0,0,1,0,0,0,0,1],"contentsRect":{"y":0,"x":0,"width":1,"height":1},"opacity":1,"edgeAntialiasingMask":251658240,"height":204.3999914690448,"hidden":false,"anchorPoint":{"pointX":0.5,"pointY":0.5}},"objectID":"939E5D0B-CBCC-4E8C-899F-C751A8CD494A","layers":[{"animations":[],"layers":[],"texturedRectangle":{"singleTextureOpacity":1,"textXHeight":0.1224354976365546,"textBaseline":0.9392314449893521,"isBackgroundTexture":true,"isVerticalText":false,"textColor":[0,0,0,1],"textureType":6},"initialState":{"affineTransform":[1,0,0,1,0,0],"masksToBounds":false,"rotation":0,"scale":1,"position":{"pointX":875.4078063964844,"pointY":84.33556886162296},"width":1752,"sublayerTransform":[1,0,0,0,0,1,0,0,0,0,1,0,0,0,0,1],"contentsRect":{"y":0,"x":0,"width":1,"height":1},"opacity":1,"edgeAntialiasingMask":0,"height":238,"hidden":false,"anchorPoint":{"pointX":0.5,"pointY":0.5}},"texture":"1500BA2D3FD472877CC669AF3A91040F"}]}]},{"animations":[],"initialState":{"affineTransform":[1,0,0,1,0,0],"masksToBounds":false,"rotation":0,"scale":1,"position":{"pointX":960,"pointY":540},"width":1920,"sublayerTransform":[1,0,0,0,0,1,0,0,0,0,1,0,0,0,0,1],"contentsRect":{"y":0,"x":0,"width":1,"height":1},"opacity":1,"edgeAntialiasingMask":251658240,"height":1080,"hidden":false,"anchorPoint":{"pointX":0.5,"pointY":0.5}},"layers":[{"animations":[],"initialState":{"affineTransform":[1,0,0,1,0,0],"masksToBounds":false,"rotation":0,"scale":1,"position":{"pointX":988.2249660491943,"pointY":68.32731008529663},"width":1676.898418426514,"sublayerTransform":[1,0,0,0,0,1,0,0,0,0,1,0,0,0,0,1],"contentsRect":{"y":0,"x":0,"width":1,"height":1},"opacity":1,"edgeAntialiasingMask":251658240,"height":168.4632635116577,"hidden":false,"anchorPoint":{"pointX":0.5,"pointY":0.5}},"objectID":"5C91F4BC-B588-4E5E-99AC-5BA1C05B0881","layers":[{"animations":[],"layers":[],"texturedRectangle":{"singleTextureOpacity":1,"textXHeight":0.5304066051136364,"textBaseline":0.7399011741984974,"isBackgroundTexture":true,"isVerticalText":false,"textColor":[0,0,0,1],"textureType":6},"initialState":{"affineTransform":[1,0,0,1,0,0],"masksToBounds":false,"rotation":0,"scale":1,"position":{"pointX":841.7242431640625,"pointY":116.9043216705322},"width":749,"sublayerTransform":[1,0,0,0,0,1,0,0,0,0,1,0,0,0,0,1],"contentsRect":{"y":0,"x":0,"width":1,"height":1},"opacity":1,"edgeAntialiasingMask":0,"height":88,"hidden":false,"anchorPoint":{"pointX":0.5,"pointY":0.5}},"texture":"5FCE00F3DF63E38504E7C0DA8D811BD5"}]}]},{"animations":[],"initialState":{"affineTransform":[1,0,0,1,0,0],"masksToBounds":false,"rotation":0,"scale":1,"position":{"pointX":960,"pointY":540},"width":1920,"sublayerTransform":[1,0,0,0,0,1,0,0,0,0,1,0,0,0,0,1],"contentsRect":{"y":0,"x":0,"width":1,"height":1},"opacity":1,"edgeAntialiasingMask":251658240,"height":1080,"hidden":false,"anchorPoint":{"pointX":0.5,"pointY":0.5}},"layers":[{"animations":[],"initialState":{"affineTransform":[1,0,0,1,0,0],"masksToBounds":false,"rotation":0,"scale":1,"position":{"pointX":988.2249683937771,"pointY":259.7144258833086},"width":1749.265549580523,"sublayerTransform":[1,0,0,0,0,1,0,0,0,0,1,0,0,0,0,1],"contentsRect":{"y":0,"x":0,"width":1,"height":1},"opacity":1,"edgeAntialiasingMask":251658240,"height":138.6999934482265,"hidden":false,"anchorPoint":{"pointX":0.5,"pointY":0.5}},"objectID":"E008FA27-5859-416D-985D-4252CC80A681","layers":[{"animations":[],"layers":[],"texturedRectangle":{"singleTextureOpacity":1,"textXHeight":0.1694165606831395,"textBaseline":0.9159132771438361,"isBackgroundTexture":true,"isVerticalText":false,"textColor":[0,0,0,1],"textureType":6},"initialState":{"affineTransform":[1,0,0,1,0,0],"masksToBounds":false,"rotation":0,"scale":1,"position":{"pointX":875.4078063964844,"pointY":51.63557084080458},"width":1752,"sublayerTransform":[1,0,0,0,0,1,0,0,0,0,1,0,0,0,0,1],"contentsRect":{"y":0,"x":0,"width":1,"height":1},"opacity":1,"edgeAntialiasingMask":0,"height":172,"hidden":true,"anchorPoint":{"pointX":0.5,"pointY":0.5}},"texture":"2D4B9D275A36EEB34B2C475DF53DFB56"}]}]},{"animations":[],"initialState":{"affineTransform":[1,0,0,1,0,0],"masksToBounds":false,"rotation":0,"scale":1,"position":{"pointX":960,"pointY":540},"width":1920,"sublayerTransform":[1,0,0,0,0,1,0,0,0,0,1,0,0,0,0,1],"contentsRect":{"y":0,"x":0,"width":1,"height":1},"opacity":1,"edgeAntialiasingMask":251658240,"height":1080,"hidden":false,"anchorPoint":{"pointX":0.5,"pointY":0.5}},"layers":[{"animations":[],"initialState":{"affineTransform":[1,0,0,1,0,0],"masksToBounds":false,"rotation":0,"scale":1,"position":{"pointX":988.2249603271482,"pointY":680.3261566162109},"width":1629.40625,"sublayerTransform":[1,0,0,0,0,1,0,0,0,0,1,0,0,0,0,1],"contentsRect":{"y":0,"x":0,"width":1,"height":1},"opacity":1,"edgeAntialiasingMask":251658240,"height":626.3125,"hidden":false,"anchorPoint":{"pointX":0.5,"pointY":0.5}},"objectID":"C23E471C-F207-4303-B037-D05480F3AB2F","layers":[{"animations":[],"layers":[],"texturedRectangle":{"isBackgroundTexture":true,"singleTextureOpacity":1,"textureType":5,"textBaseline":0,"textXHeight":0,"isVerticalText":false},"initialState":{"affineTransform":[1,0,0,1,0,0],"masksToBounds":false,"rotation":0,"scale":1,"position":{"pointX":814.4781646728518,"pointY":313.3300933837891},"width":1648,"sublayerTransform":[1,0,0,0,0,1,0,0,0,0,1,0,0,0,0,1],"contentsRect":{"y":0,"x":0,"width":1,"height":1},"opacity":1,"edgeAntialiasingMask":0,"height":645,"hidden":true,"anchorPoint":{"pointX":0.5,"pointY":0.5}},"texture":"D79AAE7B1AFA8551C9BD5FB5E9E680D2"}]}]}]}},{"effects":[{"beginTime":0,"baseLayer":{"animations":[],"initialState":{"affineTransform":[1,0,0,1,0,0],"masksToBounds":false,"rotation":0,"scale":1,"position":{"pointX":963.8984375,"pointY":734.0107116699219},"width":949.99853515625,"sublayerTransform":[1,0,0,0,0,1,0,0,0,0,1,0,0,0,0,1],"contentsRect":{"y":0,"x":0,"width":1,"height":1},"opacity":1,"edgeAntialiasingMask":251658240,"height":603.3535766601562,"hidden":false,"anchorPoint":{"pointX":0.5,"pointY":0.5}},"objectID":"F705B79F-3D80-4145-AEE6-A52BEB992010","layers":[{"animations":[],"initialState":{"affineTransform":[1,0,0,1,0,0],"masksToBounds":false,"rotation":0,"scale":1,"position":{"pointX":471.100830078125,"pointY":107.6660766601562},"width":949.99853515625,"sublayerTransform":[1,0,0,0,0,1,0,0,0,0,1,-0.0003500791246677598,0,0,0,1],"contentsRect":{"y":0,"x":0,"width":1,"height":1},"opacity":1,"edgeAntialiasingMask":251658240,"height":603.3535766601562,"hidden":false,"anchorPoint":{"pointX":0.495896375251401,"pointY":0.1784460734552006}},"layers":[{"animations":[{"timeOffset":0,"from":{"scalar":false},"beginTime":1e-100,"repeatCount":0,"fillMode":"both","property":"hidden","autoreverses":false,"duration":0.01,"to":{"scalar":true}}],"layers":[],"texturedRectangle":{"isBackgroundTexture":true,"singleTextureOpacity":1,"textureType":5,"textBaseline":0,"textXHeight":0,"isVerticalText":false},"initialState":{"affineTransform":[1,0,0,1,0,0],"masksToBounds":false,"rotation":0,"scale":1,"position":{"pointX":475.100830078125,"pointY":301.6660766601562},"width":968,"sublayerTransform":[1,0,0,0,0,1,0,0,0,0,1,0,0,0,0,1],"contentsRect":{"y":0,"x":0,"width":1,"height":1},"opacity":1,"edgeAntialiasingMask":0,"height":622,"hidden":false,"anchorPoint":{"pointX":0.5,"pointY":0.5}},"texture":"EA63DAD110C22677C2F356C304939719"}]}]},"effects":[{"beginTime":0,"baseLayer":{"animations":[],"initialState":{"affineTransform":[1,0,0,1,0,0],"masksToBounds":false,"rotation":0,"scale":1,"position":{"pointX":988.2249603271482,"pointY":680.3261566162109},"width":1629.40625,"sublayerTransform":[1,0,0,0,0,1,0,0,0,0,1,0,0,0,0,1],"contentsRect":{"y":0,"x":0,"width":1,"height":1},"opacity":1,"edgeAntialiasingMask":251658240,"height":626.3125,"hidden":false,"anchorPoint":{"pointX":0.5,"pointY":0.5}},"objectID":"C23E471C-F207-4303-B037-D05480F3AB2F","layers":[{"animations":[],"initialState":{"affineTransform":[1,0,0,1,0,0],"masksToBounds":false,"rotation":0,"scale":1,"position":{"pointX":786.4781646728518,"pointY":172.8300933837891},"width":1629.40625,"sublayerTransform":[1,0,0,0,0,1,0,0,0,0,1,-0.0003500791246677598,0,0,0,1],"contentsRect":{"y":0,"x":0,"width":1,"height":1},"opacity":1,"edgeAntialiasingMask":251658240,"height":626.3125,"hidden":false,"anchorPoint":{"pointX":0.4826777635551918,"pointY":0.2759486572338714}},"layers":[{"animations":[{"timeOffset":0,"from":{"scalar":true},"beginTime":1e-100,"repeatCount":0,"fillMode":"both","property":"hidden","autoreverses":false,"duration":0.01,"to":{"scalar":false}}],"layers":[],"texturedRectangle":{"isBackgroundTexture":true,"singleTextureOpacity":1,"textureType":5,"textBaseline":0,"textXHeight":0,"isVerticalText":false},"initialState":{"affineTransform":[1,0,0,1,0,0],"masksToBounds":false,"rotation":0,"scale":1,"position":{"pointX":814.4781646728518,"pointY":313.3300933837891},"width":1648,"sublayerTransform":[1,0,0,0,0,1,0,0,0,0,1,0,0,0,0,1],"contentsRect":{"y":0,"x":0,"width":1,"height":1},"opacity":1,"edgeAntialiasingMask":0,"height":645,"hidden":true,"anchorPoint":{"pointX":0.5,"pointY":0.5}},"texture":"D79AAE7B1AFA8551C9BD5FB5E9E680D2"}]}]},"effects":[],"duration":0.01,"type":"buildIn","name":"apple:appear","objectID":"C23E471C-F207-4303-B037-D05480F3AB2F"}],"duration":0.01,"type":"buildOut","name":"apple:appear","objectID":"F705B79F-3D80-4145-AEE6-A52BEB992010"}],"automaticPlay":false,"hyperlinks":[],"accessibility":[{"text":"Delta morphology","targetRectangle":{"y":31.72067832946777,"x":612.0501708984375,"width":752.349609375,"height":115}},{"text":"School of Geosciences","targetRectangle":{"y":1039.375854492188,"x":1701.960205078125,"width":199.053955078125,"height":25}},{"text":"Inactive areas, which may form lobes or just parts of the delta, typically subside and are reworked by tidal currents and waves. ","targetRectangle":{"y":190.3644291591954,"x":165.1199706792831,"width":1697.73772585392,"height":138.6999982595444}},{"text":"coast2000kolb.jpg","targetRectangle":{"y":432.3339233398438,"x":488.899169921875,"width":949.99853515625,"height":603.3535766601562}}],"baseLayer":{"animations":[],"initialState":{"affineTransform":[1,0,0,1,0,0],"masksToBounds":false,"rotation":0,"scale":1,"position":{"pointX":960,"pointY":540},"width":1920,"sublayerTransform":[1,0,0,0,0,1,0,0,0,0,1,0,0,0,0,1],"contentsRect":{"y":0,"x":0,"width":1,"height":1},"opacity":1,"edgeAntialiasingMask":251658240,"height":1080,"hidden":false,"anchorPoint":{"pointX":0.5,"pointY":0.5}},"layers":[{"animations":[],"initialState":{"affineTransform":[1,0,0,1,0,0],"masksToBounds":false,"rotation":0,"scale":1,"position":{"pointX":960,"pointY":540},"width":1920,"sublayerTransform":[1,0,0,0,0,1,0,0,0,0,1,0,0,0,0,1],"contentsRect":{"y":0,"x":0,"width":1,"height":1},"opacity":1,"edgeAntialiasingMask":251658240,"height":1080,"hidden":false,"anchorPoint":{"pointX":0.5,"pointY":0.5}},"layers":[{"animations":[],"initialState":{"affineTransform":[1,0,0,1,0,0],"masksToBounds":false,"rotation":0,"scale":1,"position":{"pointX":960,"pointY":540},"width":1920,"sublayerTransform":[1,0,0,0,0,1,0,0,0,0,1,0,0,0,0,1],"contentsRect":{"y":0,"x":0,"width":1,"height":1},"opacity":1,"edgeAntialiasingMask":251658240,"height":1080,"hidden":false,"anchorPoint":{"pointX":0.5,"pointY":0.5}},"layers":[{"animations":[],"layers":[],"texturedRectangle":{"isBackgroundTexture":true,"singleTextureOpacity":1,"textureType":1,"textBaseline":0,"textXHeight":0,"isVerticalText":false},"initialState":{"affineTransform":[1,0,0,1,0,0],"masksToBounds":false,"rotation":0,"scale":1,"position":{"pointX":960,"pointY":540},"width":1920,"sublayerTransform":[1,0,0,0,0,1,0,0,0,0,1,0,0,0,0,1],"contentsRect":{"y":0,"x":0,"width":1,"height":1},"opacity":1,"edgeAntialiasingMask":0,"height":1080,"hidden":false,"anchorPoint":{"pointX":0.5,"pointY":0.5}},"texture":"C25C25FF361FB24FC35F6B120D2F252D"}]}]},{"animations":[],"initialState":{"affineTransform":[1,0,0,1,0,0],"masksToBounds":false,"rotation":0,"scale":1,"position":{"pointX":960,"pointY":540},"width":1920,"sublayerTransform":[1,0,0,0,0,1,0,0,0,0,1,0,0,0,0,1],"contentsRect":{"y":0,"x":0,"width":1,"height":1},"opacity":1,"edgeAntialiasingMask":251658240,"height":1080,"hidden":false,"anchorPoint":{"pointX":0.5,"pointY":0.5}},"layers":[{"animations":[],"initialState":{"affineTransform":[1,0,0,1,0,0],"masksToBounds":false,"rotation":0,"scale":1,"position":{"pointX":963.8984375,"pointY":734.0107116699219},"width":949.99853515625,"sublayerTransform":[1,0,0,0,0,1,0,0,0,0,1,0,0,0,0,1],"contentsRect":{"y":0,"x":0,"width":1,"height":1},"opacity":1,"edgeAntialiasingMask":251658240,"height":603.3535766601562,"hidden":false,"anchorPoint":{"pointX":0.5,"pointY":0.5}},"objectID":"F705B79F-3D80-4145-AEE6-A52BEB992010","layers":[{"animations":[],"layers":[],"texturedRectangle":{"isBackgroundTexture":true,"singleTextureOpacity":1,"textureType":5,"textBaseline":0,"textXHeight":0,"isVerticalText":false},"initialState":{"affineTransform":[1,0,0,1,0,0],"masksToBounds":false,"rotation":0,"scale":1,"position":{"pointX":475.100830078125,"pointY":301.6660766601562},"width":968,"sublayerTransform":[1,0,0,0,0,1,0,0,0,0,1,0,0,0,0,1],"contentsRect":{"y":0,"x":0,"width":1,"height":1},"opacity":1,"edgeAntialiasingMask":0,"height":622,"hidden":false,"anchorPoint":{"pointX":0.5,"pointY":0.5}},"texture":"EA63DAD110C22677C2F356C304939719"}]}]},{"animations":[],"initialState":{"affineTransform":[1,0,0,1,0,0],"masksToBounds":false,"rotation":0,"scale":1,"position":{"pointX":960,"pointY":540},"width":1920,"sublayerTransform":[1,0,0,0,0,1,0,0,0,0,1,0,0,0,0,1],"contentsRect":{"y":0,"x":0,"width":1,"height":1},"opacity":1,"edgeAntialiasingMask":251658240,"height":1080,"hidden":false,"anchorPoint":{"pointX":0.5,"pointY":0.5}},"layers":[{"animations":[],"initialState":{"affineTransform":[1,0,0,1,0,0],"masksToBounds":false,"rotation":0,"scale":1,"position":{"pointX":1801.487178325653,"pointY":1053.904336541891},"width":211.8828039169312,"sublayerTransform":[1,0,0,0,0,1,0,0,0,0,1,0,0,0,0,1],"contentsRect":{"y":0,"x":0,"width":1,"height":1},"opacity":1,"edgeAntialiasingMask":251658240,"height":40.3069640994072,"hidden":false,"anchorPoint":{"pointX":0.5,"pointY":0.5}},"objectID":"6B8CF862-225A-49B5-AF89-FBF00406E318","layers":[{"animations":[],"layers":[],"texturedRectangle":{"singleTextureOpacity":1,"textXHeight":0.3554771686422414,"textBaseline":0.5821617389547413,"isBackgroundTexture":true,"isVerticalText":false,"textColor":[0,0,0,1],"textureType":6},"initialState":{"affineTransform":[1,0,0,1,0,0],"masksToBounds":false,"rotation":0,"scale":1,"position":{"pointX":110.9542236328125,"pointY":22.7491455078125},"width":211,"sublayerTransform":[1,0,0,0,0,1,0,0,0,0,1,0,0,0,0,1],"contentsRect":{"y":0,"x":0,"width":1,"height":1},"opacity":1,"edgeAntialiasingMask":0,"height":29,"hidden":false,"anchorPoint":{"pointX":0.5,"pointY":0.5}},"texture":"634618DBDF2F96BD355070A8377C1141"}]}]},{"animations":[],"initialState":{"affineTransform":[1,0,0,1,0,0],"masksToBounds":false,"rotation":0,"scale":1,"position":{"pointX":960,"pointY":540},"width":1920,"sublayerTransform":[1,0,0,0,0,1,0,0,0,0,1,0,0,0,0,1],"contentsRect":{"y":0,"x":0,"width":1,"height":1},"opacity":1,"edgeAntialiasingMask":251658240,"height":1080,"hidden":false,"anchorPoint":{"pointX":0.5,"pointY":0.5}},"layers":[{"animations":[],"initialState":{"affineTransform":[1,0,0,1,0,0],"masksToBounds":false,"rotation":0,"scale":1,"position":{"pointX":988.2249683937771,"pointY":292.8644268728995},"width":1749.265549580523,"sublayerTransform":[1,0,0,0,0,1,0,0,0,0,1,0,0,0,0,1],"contentsRect":{"y":0,"x":0,"width":1,"height":1},"opacity":1,"edgeAntialiasingMask":251658240,"height":204.3999914690448,"hidden":false,"anchorPoint":{"pointX":0.5,"pointY":0.5}},"objectID":"939E5D0B-CBCC-4E8C-899F-C751A8CD494A","layers":[{"animations":[],"layers":[],"texturedRectangle":{"singleTextureOpacity":1,"textXHeight":0.1224354976365546,"textBaseline":0.9392314449893521,"isBackgroundTexture":true,"isVerticalText":false,"textColor":[0,0,0,1],"textureType":6},"initialState":{"affineTransform":[1,0,0,1,0,0],"masksToBounds":false,"rotation":0,"scale":1,"position":{"pointX":875.4078063964844,"pointY":84.33556886162296},"width":1752,"sublayerTransform":[1,0,0,0,0,1,0,0,0,0,1,0,0,0,0,1],"contentsRect":{"y":0,"x":0,"width":1,"height":1},"opacity":1,"edgeAntialiasingMask":0,"height":238,"hidden":true,"anchorPoint":{"pointX":0.5,"pointY":0.5}},"texture":"1500BA2D3FD472877CC669AF3A91040F"}]}]},{"animations":[],"initialState":{"affineTransform":[1,0,0,1,0,0],"masksToBounds":false,"rotation":0,"scale":1,"position":{"pointX":960,"pointY":540},"width":1920,"sublayerTransform":[1,0,0,0,0,1,0,0,0,0,1,0,0,0,0,1],"contentsRect":{"y":0,"x":0,"width":1,"height":1},"opacity":1,"edgeAntialiasingMask":251658240,"height":1080,"hidden":false,"anchorPoint":{"pointX":0.5,"pointY":0.5}},"layers":[{"animations":[],"initialState":{"affineTransform":[1,0,0,1,0,0],"masksToBounds":false,"rotation":0,"scale":1,"position":{"pointX":988.2249660491943,"pointY":68.32731008529663},"width":1676.898418426514,"sublayerTransform":[1,0,0,0,0,1,0,0,0,0,1,0,0,0,0,1],"contentsRect":{"y":0,"x":0,"width":1,"height":1},"opacity":1,"edgeAntialiasingMask":251658240,"height":168.4632635116577,"hidden":false,"anchorPoint":{"pointX":0.5,"pointY":0.5}},"objectID":"5C91F4BC-B588-4E5E-99AC-5BA1C05B0881","layers":[{"animations":[],"layers":[],"texturedRectangle":{"singleTextureOpacity":1,"textXHeight":0.5304066051136364,"textBaseline":0.7399011741984974,"isBackgroundTexture":true,"isVerticalText":false,"textColor":[0,0,0,1],"textureType":6},"initialState":{"affineTransform":[1,0,0,1,0,0],"masksToBounds":false,"rotation":0,"scale":1,"position":{"pointX":841.7242431640625,"pointY":116.9043216705322},"width":749,"sublayerTransform":[1,0,0,0,0,1,0,0,0,0,1,0,0,0,0,1],"contentsRect":{"y":0,"x":0,"width":1,"height":1},"opacity":1,"edgeAntialiasingMask":0,"height":88,"hidden":false,"anchorPoint":{"pointX":0.5,"pointY":0.5}},"texture":"5FCE00F3DF63E38504E7C0DA8D811BD5"}]}]},{"animations":[],"initialState":{"affineTransform":[1,0,0,1,0,0],"masksToBounds":false,"rotation":0,"scale":1,"position":{"pointX":960,"pointY":540},"width":1920,"sublayerTransform":[1,0,0,0,0,1,0,0,0,0,1,0,0,0,0,1],"contentsRect":{"y":0,"x":0,"width":1,"height":1},"opacity":1,"edgeAntialiasingMask":251658240,"height":1080,"hidden":false,"anchorPoint":{"pointX":0.5,"pointY":0.5}},"layers":[{"animations":[],"initialState":{"affineTransform":[1,0,0,1,0,0],"masksToBounds":false,"rotation":0,"scale":1,"position":{"pointX":988.2249683937771,"pointY":259.7144258833086},"width":1749.265549580523,"sublayerTransform":[1,0,0,0,0,1,0,0,0,0,1,0,0,0,0,1],"contentsRect":{"y":0,"x":0,"width":1,"height":1},"opacity":1,"edgeAntialiasingMask":251658240,"height":138.6999934482265,"hidden":false,"anchorPoint":{"pointX":0.5,"pointY":0.5}},"objectID":"E008FA27-5859-416D-985D-4252CC80A681","layers":[{"animations":[],"layers":[],"texturedRectangle":{"singleTextureOpacity":1,"textXHeight":0.1694165606831395,"textBaseline":0.9159132771438361,"isBackgroundTexture":true,"isVerticalText":false,"textColor":[0,0,0,1],"textureType":6},"initialState":{"affineTransform":[1,0,0,1,0,0],"masksToBounds":false,"rotation":0,"scale":1,"position":{"pointX":875.4078063964844,"pointY":51.63557084080458},"width":1752,"sublayerTransform":[1,0,0,0,0,1,0,0,0,0,1,0,0,0,0,1],"contentsRect":{"y":0,"x":0,"width":1,"height":1},"opacity":1,"edgeAntialiasingMask":0,"height":172,"hidden":false,"anchorPoint":{"pointX":0.5,"pointY":0.5}},"texture":"2D4B9D275A36EEB34B2C475DF53DFB56"}]}]},{"animations":[],"initialState":{"affineTransform":[1,0,0,1,0,0],"masksToBounds":false,"rotation":0,"scale":1,"position":{"pointX":960,"pointY":540},"width":1920,"sublayerTransform":[1,0,0,0,0,1,0,0,0,0,1,0,0,0,0,1],"contentsRect":{"y":0,"x":0,"width":1,"height":1},"opacity":1,"edgeAntialiasingMask":251658240,"height":1080,"hidden":false,"anchorPoint":{"pointX":0.5,"pointY":0.5}},"layers":[{"animations":[],"initialState":{"affineTransform":[1,0,0,1,0,0],"masksToBounds":false,"rotation":0,"scale":1,"position":{"pointX":988.2249603271482,"pointY":680.3261566162109},"width":1629.40625,"sublayerTransform":[1,0,0,0,0,1,0,0,0,0,1,0,0,0,0,1],"contentsRect":{"y":0,"x":0,"width":1,"height":1},"opacity":1,"edgeAntialiasingMask":251658240,"height":626.3125,"hidden":false,"anchorPoint":{"pointX":0.5,"pointY":0.5}},"objectID":"C23E471C-F207-4303-B037-D05480F3AB2F","layers":[{"animations":[],"layers":[],"texturedRectangle":{"isBackgroundTexture":true,"singleTextureOpacity":1,"textureType":5,"textBaseline":0,"textXHeight":0,"isVerticalText":false},"initialState":{"affineTransform":[1,0,0,1,0,0],"masksToBounds":false,"rotation":0,"scale":1,"position":{"pointX":814.4781646728518,"pointY":313.3300933837891},"width":1648,"sublayerTransform":[1,0,0,0,0,1,0,0,0,0,1,0,0,0,0,1],"contentsRect":{"y":0,"x":0,"width":1,"height":1},"opacity":1,"edgeAntialiasingMask":0,"height":645,"hidden":true,"anchorPoint":{"pointX":0.5,"pointY":0.5}},"texture":"D79AAE7B1AFA8551C9BD5FB5E9E680D2"}]}]}]}},{"effects":[{"beginTime":0,"baseLayer":{"animations":[],"initialState":{"affineTransform":[1,0,0,1,0,0],"masksToBounds":false,"rotation":0,"scale":1,"position":{"pointX":960,"pointY":540},"width":1920,"sublayerTransform":[1,0,0,0,0,1,0,0,0,0,1,0,0,0,0,1],"contentsRect":{"y":0,"x":0,"width":1,"height":1},"opacity":1,"edgeAntialiasingMask":251658240,"height":1080,"hidden":false,"anchorPoint":{"pointX":0.5,"pointY":0.5}},"objectID":"0","layers":[{"animations":[],"initialState":{"affineTransform":[1,0,0,1,0,0],"masksToBounds":false,"rotation":0,"scale":1,"position":{"pointX":960,"pointY":540},"width":1920,"sublayerTransform":[1,0,0,0,0,1,0,0,0,0,1,-0.0003500791246677598,0,0,0,1],"contentsRect":{"y":0,"x":0,"width":1,"height":1},"opacity":1,"edgeAntialiasingMask":251658240,"height":1080,"hidden":false,"anchorPoint":{"pointX":0.5,"pointY":0.5}},"layers":[{"animations":[],"layers":[],"texturedRectangle":{"isBackgroundTexture":false,"singleTextureOpacity":1,"textureType":0,"textBaseline":0,"textXHeight":0,"isVerticalText":false},"initialState":{"affineTransform":[1,0,0,1,0,0],"masksToBounds":false,"rotation":0,"scale":1,"position":{"pointX":960,"pointY":540},"width":1920,"sublayerTransform":[1,0,0,0,0,1,0,0,0,0,1,0,0,0,0,1],"contentsRect":{"y":0,"x":0,"width":1,"height":1},"opacity":1,"edgeAntialiasingMask":0,"height":1080,"hidden":false,"anchorPoint":{"pointX":0.5,"pointY":0.5}},"texture":"A324682FF46FB156BE950BD2455312FC"},{"animations":[{"timeOffset":0,"from":{"scalar":false},"beginTime":0,"repeatCount":0,"fillMode":"both","property":"hidden","autoreverses":false,"duration":0.01,"to":{"scalar":true}}],"layers":[],"texturedRectangle":{"isBackgroundTexture":false,"singleTextureOpacity":1,"textureType":0,"textBaseline":0,"textXHeight":0,"isVerticalText":false},"initialState":{"affineTransform":[1,0,0,1,0,0],"masksToBounds":false,"rotation":0,"scale":1,"position":{"pointX":960,"pointY":540},"width":1920,"sublayerTransform":[1,0,0,0,0,1,0,0,0,0,1,0,0,0,0,1],"contentsRect":{"y":0,"x":0,"width":1,"height":1},"opacity":1,"edgeAntialiasingMask":0,"height":1080,"hidden":false,"anchorPoint":{"pointX":0.5,"pointY":0.5}},"texture":"62358F665A19968F6EA1D3132EDD5855"}]}]},"effects":[],"duration":0.01,"type":"transition","name":"none","objectID":"0"}],"automaticPlay":false,"hyperlinks":[],"accessibility":[{"text":"Delta morphology","targetRectangle":{"y":31.72067832946777,"x":612.0501708984375,"width":752.349609375,"height":115}},{"text":"School of Geosciences","targetRectangle":{"y":1039.375854492188,"x":1701.960205078125,"width":199.053955078125,"height":25}},{"text":"Inactive areas, which may form lobes or just parts of the delta, typically subside and are reworked by tidal currents and waves. ","targetRectangle":{"y":190.3644291591954,"x":165.1199706792831,"width":1697.73772585392,"height":138.6999982595444}},{"text":"Screen Shot 2016-11-09 at 8.05.00 am.png","targetRectangle":{"y":367.1699066162109,"x":173.5218353271482,"width":1629.40625,"height":626.3125}}],"baseLayer":{"animations":[],"initialState":{"affineTransform":[1,0,0,1,0,0],"masksToBounds":false,"rotation":0,"scale":1,"position":{"pointX":960,"pointY":540},"width":1920,"sublayerTransform":[1,0,0,0,0,1,0,0,0,0,1,0,0,0,0,1],"contentsRect":{"y":0,"x":0,"width":1,"height":1},"opacity":1,"edgeAntialiasingMask":251658240,"height":1080,"hidden":false,"anchorPoint":{"pointX":0.5,"pointY":0.5}},"objectID":"0","layers":[{"animations":[],"initialState":{"affineTransform":[1,0,0,1,0,0],"masksToBounds":false,"rotation":0,"scale":1,"position":{"pointX":960,"pointY":540},"width":1920,"sublayerTransform":[1,0,0,0,0,1,0,0,0,0,1,-0.0003500791246677598,0,0,0,1],"contentsRect":{"y":0,"x":0,"width":1,"height":1},"opacity":1,"edgeAntialiasingMask":251658240,"height":1080,"hidden":false,"anchorPoint":{"pointX":0.5,"pointY":0.5}},"layers":[{"animations":[],"layers":[],"texturedRectangle":{"isBackgroundTexture":false,"singleTextureOpacity":1,"textureType":0,"textBaseline":0,"textXHeight":0,"isVerticalText":false},"initialState":{"affineTransform":[1,0,0,1,0,0],"masksToBounds":false,"rotation":0,"scale":1,"position":{"pointX":960,"pointY":540},"width":1920,"sublayerTransform":[1,0,0,0,0,1,0,0,0,0,1,0,0,0,0,1],"contentsRect":{"y":0,"x":0,"width":1,"height":1},"opacity":1,"edgeAntialiasingMask":0,"height":1080,"hidden":false,"anchorPoint":{"pointX":0.5,"pointY":0.5}},"texture":"62358F665A19968F6EA1D3132EDD5855"}]}]}}]}